render_swagger.py
mkdocs_render_swagger_plugin-0.1.1.dist-info/LICENSE
mkdocs_render_swagger_plugin-0.1.1.dist-info/METADATA
mkdocs_render_swagger_plugin-0.1.1.dist-info/WHEEL
mkdocs_render_swagger_plugin-0.1.1.dist-info/entry_points.txt
mkdocs_render_swagger_plugin-0.1.1.dist-info/top_level.txt
mkdocs_render_swagger_plugin-0.1.1.dist-info/RECORD
