Metadata-Version: 2.1
Name: mkdocs-render-swagger-plugin
Version: 0.1.1
Summary: MKDocs plugin for rendering swagger & openapi files.
Home-page: https://github.com/bharel/mkdocs-render-swagger-plugin
Author: Bar Harel
Author-email: bzvi7919@gmail.com
Classifier: Programming Language :: Python :: 3
Classifier: License :: OSI Approved :: MIT License
Classifier: Operating System :: OS Independent
Requires-Python: >=3.8
License-File: LICENSE
Requires-Dist: mkdocs >=1.4
Provides-Extra: dev
Requires-Dist: flake8 ; extra == 'dev'
Requires-Dist: mypy ; extra == 'dev'
Requires-Dist: pyyaml ; extra == 'dev'
Requires-Dist: coverage ; extra == 'dev'
